homeconnect_webthing/__init__.py
homeconnect_webthing/app.py
homeconnect_webthing/appliances.py
homeconnect_webthing/appliances_webthing.py
homeconnect_webthing/auth.py
homeconnect_webthing/auth_manager.py
homeconnect_webthing/eventstream.py
homeconnect_webthing/homeconnect.py
homeconnect_webthing/utils.py
homeconnect_webthing-1.0.6.dist-info/LICENSE
homeconnect_webthing-1.0.6.dist-info/METADATA
homeconnect_webthing-1.0.6.dist-info/WHEEL
homeconnect_webthing-1.0.6.dist-info/entry_points.txt
homeconnect_webthing-1.0.6.dist-info/top_level.txt
homeconnect_webthing-1.0.6.dist-info/RECORD
