Metadata-Version: 2.1
Name: homeconnect_webthing
Version: 1.0.6
Summary: Homeconnect WebThing adapter
Author: Gregor Roth
Author-email: gregor.roth@web.de
Requires-Python: >=3.8
License-File: LICENSE
Requires-Dist: sseclient-py >=1.7.2
Requires-Dist: requests
Requires-Dist: webthing >=0.15.0
Requires-Dist: appdirs ==1.4.4
Requires-Dist: redzoo ==0.3.7
